pylastfmapi/__init__.py
pylastfmapi/client.py
pylastfmapi/constants.py
pylastfmapi/exceptions.py
pylastfmapi/main.py
pylastfmapi/request.py
pylastfmapi/settings.py
pylastfmapi/typehints.py
pylastfmapi/utils.py
pylastfmapi-0.1.0.dist-info/LICENSE
pylastfmapi-0.1.0.dist-info/METADATA
pylastfmapi-0.1.0.dist-info/WHEEL
pylastfmapi-0.1.0.dist-info/RECORD
