Metadata-Version: 2.1
Name: pylastfmapi
Version: 0.1.0
Summary: An API library to interact with the LastFM API written in Python
License: MIT
Author: William Felipe
Author-email: theorangewill@gmail.com
Requires-Python: >=3.12,<4.0
Classifier: Intended Audience :: Developers
Classifier: License :: OSI Approved :: MIT License
Classifier: Programming Language :: Python :: 3
Classifier: Programming Language :: Python :: 3.12
Classifier: Topic :: Software Development :: Libraries :: Python Modules
Classifier: Topic :: Utilities
Requires-Dist: requests (>=2.32.3,<3.0.0)
Requires-Dist: requests-cache (>=1.2.1,<2.0.0)
Project-URL: Docmentation, https://pylastfmapi.readthedocs.io/en/latest/
Project-URL: Repository, https://github.com/theorangewill/pylastfmapi
